{"dBhprzkgb/HVkBMMMpnmsg==":"pic-mas-1-2049-1236x1326.png","H6BWLl3TPQlvl4XxxOmp4g==":"a0f7a352284667.590b3416801fc-1400x808.jpg","FNu+vc4ZLwNdoG/0X8QWMQ==":"a0f7a352284667.590b3416801fc-1400x808.jpeg","cygoYG/CinFEaV9q1pzQHA==":"a0f7a352284667.590b3416801fc-1-1400x808.jpeg","MOoPpM2nt13ME6peheZOjA==":"a0f7a352284667.590b3416801fc-2-1400x808.jpeg","xs1VCyJ+mzYyGbDUeCcrYw==":"a0f7a352284667.590b3416801fc-3-1400x808.jpeg","DSPWjJprucLag7RZ1GQRUQ==":"a0f7a352284667.590b3416801fc-4-1400x808.jpeg","QqmJlhXhb0Gwmxo8cJO+bg==":"a0f7a352284667.590b3416801fc-5-1400x808.jpeg","9tuGvrJ6b6rrgmO67K2+BA==":"icon-2-400x300.png","D3rgvUHhCvdmPNYD2veo8Q==":"icon-1-400x300.png","9MGjLJYtwjbEw+cFWUzF0g==":"icon-3-400x300.png","JalG+EJ55Eg+gXiiE4WLsQ==":"g1-3-1080x1080.png","2YZFvrN5fR4ZZ+rz3+XxQQ==":"icon-13.png","SzAyZjiUOQJ4fM27gNXwBw==":"icon-10.png","L+53m6EAuEp7XiWsjidRAw==":"icon-11.png","9VQUTXwXepO4yWUz2TtmMw==":"icon-16.png","lJ5MIAwXVP40sN2ZQytWhg==":"icon-14.png","t3ZXafrl/3ZwhY5WspfVkw==":"icon-15.png","cdGXrFjUwDCQs8J2yD+CmA==":"ehkspress-dostavka-900x735.png","dqNrtBhQUz9wEWd5B/wvHw==":"3610314-1500x1000.jpg","vtIcG3mIugO2/MSCjE8bjw==":"799547-fullimage-1080x1080.png","cnHA8NrbHFW8bSDfgB9wkg==":"44a76deb298d028d17278e8bc63a52e9-800x449.jpg","L1Pe98bT/IwPMvzuMhVhWw==":"icon-3-96x72.png","inraYjY0BzXIUy/QbAdhCQ==":"icon-4-96x72.png","X2tJqV55bVKUwfNlkWVDHQ==":"icon-5-96x72.png","wqnv3SAcoM3o6jA6Wz9/aA==":"icon-3-179x134.png"}